{
  "id": "gallery",
  "label": "Gallery",
  "icon": "images",
  "order": 3,
  "i18n": {
    "en": "Gallery",
    "vi": "Thư viện ảnh"
  },
  "types": [
    {
      "id": "gallery-grid",
      "label": "Gallery",
      "order": 0,
      "layout": "preview",
      "i18n": { "en": "Gallery", "vi": "Thư viện ảnh" },
      "items": [
        {
          "id": "gallery-grid-basic",
          "componentType": "GalleryPro",
          "name": "Grid",
          "thumbnail": null,
          "i18n": { "en": { "name": "Grid" }, "vi": { "name": "Lưới" } },
          "props": { "layoutMode": "grid", "columns": 3, "gap": 12, "aspectRatio": "1/1" },
          "tags": ["gallery", "grid"]
        },
        {
          "id": "gallery-masonry",
          "componentType": "GalleryPro",
          "name": "Masonry",
          "thumbnail": null,
          "i18n": { "en": { "name": "Masonry" }, "vi": { "name": "Masonry" } },
          "props": { "layoutMode": "masonry", "columns": 3, "gap": 12 },
          "tags": ["gallery", "masonry", "pinterest"]
        },
        {
          "id": "gallery-collage",
          "componentType": "GalleryPro",
          "name": "Collage",
          "thumbnail": null,
          "i18n": { "en": { "name": "Collage" }, "vi": { "name": "Ghép ảnh" } },
          "props": { "layoutMode": "collage", "gap": 8 },
          "tags": ["gallery", "collage", "mosaic"]
        },
        {
          "id": "gallery-thumbnails",
          "componentType": "GalleryPro",
          "name": "Thumbnails",
          "thumbnail": null,
          "i18n": { "en": { "name": "Thumbnails" }, "vi": { "name": "Xem nhanh" } },
          "props": { "layoutMode": "thumbnails", "gap": 8 },
          "tags": ["gallery", "thumbnails", "filmstrip"]
        },
        {
          "id": "gallery-strip",
          "componentType": "GalleryPro",
          "name": "Strip",
          "thumbnail": null,
          "i18n": { "en": { "name": "Strip" }, "vi": { "name": "Dải ngang" } },
          "props": { "layoutMode": "strip", "gap": 8 },
          "tags": ["gallery", "strip", "editorial"]
        },
        {
          "id": "gallery-column",
          "componentType": "GalleryPro",
          "name": "Column",
          "thumbnail": null,
          "i18n": { "en": { "name": "Column" }, "vi": { "name": "Cột" } },
          "props": { "layoutMode": "column", "gap": 12 },
          "tags": ["gallery", "column"]
        },
        {
          "id": "gallery-bricks",
          "componentType": "GalleryPro",
          "name": "Bricks",
          "thumbnail": null,
          "i18n": { "en": { "name": "Bricks" }, "vi": { "name": "Gạch" } },
          "props": { "layoutMode": "bricks", "gap": 8, "aspectRatio": "4/3" },
          "tags": ["gallery", "bricks", "metro"]
        },
        {
          "id": "gallery-honeycomb",
          "componentType": "GalleryPro",
          "name": "Honeycomb",
          "thumbnail": null,
          "i18n": { "en": { "name": "Honeycomb" }, "vi": { "name": "Tổ ong" } },
          "props": { "layoutMode": "honeycomb", "columns": 4, "gap": 8 },
          "tags": ["gallery", "honeycomb", "hexagon", "creative"]
        },
        {
          "id": "gallery-freestyle",
          "componentType": "GalleryPro",
          "name": "Freestyle",
          "thumbnail": null,
          "i18n": { "en": { "name": "Freestyle" }, "vi": { "name": "Ngẫu nhiên" } },
          "props": { "layoutMode": "freestyle", "columns": 3 },
          "tags": ["gallery", "freestyle", "scattered", "creative"]
        },
        {
          "id": "gallery-stacked",
          "componentType": "GalleryPro",
          "name": "Stacked",
          "thumbnail": null,
          "i18n": { "en": { "name": "Stacked" }, "vi": { "name": "Xếp chồng" } },
          "props": { "layoutMode": "stacked" },
          "tags": ["gallery", "stacked", "cards", "depth"]
        }
      ]
    },
    {
      "id": "gallery-carousel",
      "label": "Carousel",
      "order": 1,
      "layout": "preview",
      "i18n": { "en": "Carousel", "vi": "Băng chuyền" },
      "items": [
        {
          "id": "gallery-slider",
          "componentType": "GalleryPro",
          "name": "Slider",
          "thumbnail": null,
          "i18n": { "en": { "name": "Slider" }, "vi": { "name": "Slider" } },
          "props": { "layoutMode": "slider", "carouselConfig": { "effect": "slide", "aspectRatio": "16/9", "slidesPerView": 1 } },
          "tags": ["gallery", "slider", "carousel"]
        },
        {
          "id": "gallery-slider-square",
          "componentType": "GalleryPro",
          "name": "Slider Square",
          "thumbnail": null,
          "i18n": { "en": { "name": "Slider Square" }, "vi": { "name": "Slider vuông" } },
          "props": { "layoutMode": "slider", "carouselConfig": { "effect": "slide", "aspectRatio": "1/1", "slidesPerView": 1 } },
          "tags": ["gallery", "slider", "square"]
        },
        {
          "id": "gallery-slider-fade",
          "componentType": "GalleryPro",
          "name": "Fade",
          "thumbnail": null,
          "i18n": { "en": { "name": "Fade" }, "vi": { "name": "Mờ dần" } },
          "props": { "layoutMode": "slider", "carouselConfig": { "effect": "fade", "fadeCrossFade": true, "aspectRatio": "16/9" } },
          "tags": ["gallery", "slider", "fade", "transition"]
        },
        {
          "id": "gallery-slider-peek",
          "componentType": "GalleryPro",
          "name": "Peek",
          "thumbnail": null,
          "i18n": { "en": { "name": "Peek" }, "vi": { "name": "Hé lộ" } },
          "props": { "layoutMode": "slider", "carouselConfig": { "effect": "slide", "slidesPerView": 1.15, "centeredSlides": true, "spaceBetween": 16, "slideRadius": 8 } },
          "tags": ["gallery", "slider", "peek"]
        },
        {
          "id": "gallery-slider-multi",
          "componentType": "GalleryPro",
          "name": "Multi-Slide",
          "thumbnail": null,
          "i18n": { "en": { "name": "Multi-Slide" }, "vi": { "name": "Nhiều slide" } },
          "props": { "layoutMode": "slider", "carouselConfig": { "effect": "slide", "slidesPerView": 2.5, "spaceBetween": 16, "centeredSlides": true, "slideRadius": 4 } },
          "tags": ["gallery", "slider", "multi"]
        },
        {
          "id": "gallery-slider-cards",
          "componentType": "GalleryPro",
          "name": "Card Stack",
          "thumbnail": null,
          "i18n": { "en": { "name": "Card Stack" }, "vi": { "name": "Xếp thẻ" } },
          "props": { "layoutMode": "slider", "carouselConfig": { "effect": "cards", "centeredSlides": true, "slideRadius": 12 } },
          "tags": ["gallery", "slider", "cards", "stack"]
        },
        {
          "id": "gallery-slider-coverflow",
          "componentType": "GalleryPro",
          "name": "Coverflow",
          "thumbnail": null,
          "i18n": { "en": { "name": "Coverflow" }, "vi": { "name": "Coverflow" } },
          "props": { "layoutMode": "slider", "carouselConfig": { "effect": "coverflow", "centeredSlides": true, "slidesPerView": 3, "coverflowEffect": { "rotate": 50, "stretch": 0, "depth": 100, "modifier": 1, "scale": 1, "slideShadows": true } } },
          "tags": ["gallery", "slider", "coverflow", "3d"]
        },
        {
          "id": "gallery-slider-cube",
          "componentType": "GalleryPro",
          "name": "Cube",
          "thumbnail": null,
          "i18n": { "en": { "name": "Cube" }, "vi": { "name": "Khối lập phương" } },
          "props": { "layoutMode": "slider", "carouselConfig": { "effect": "cube", "cubeEffect": { "shadow": true, "slideShadows": true, "shadowOffset": 20, "shadowScale": 0.94 } } },
          "tags": ["gallery", "slider", "cube", "3d"]
        },
        {
          "id": "gallery-slider-flip",
          "componentType": "GalleryPro",
          "name": "Flip",
          "thumbnail": null,
          "i18n": { "en": { "name": "Flip" }, "vi": { "name": "Lật trang" } },
          "props": { "layoutMode": "slider", "carouselConfig": { "effect": "flip", "flipSlideShadows": true } },
          "tags": ["gallery", "slider", "flip"]
        },
        {
          "id": "gallery-slideshow",
          "componentType": "GalleryPro",
          "name": "Slideshow",
          "thumbnail": null,
          "i18n": { "en": { "name": "Slideshow" }, "vi": { "name": "Trình chiếu tự động" } },
          "props": { "layoutMode": "slideshow", "carouselConfig": { "autoplay": { "enabled": true, "delay": 3000, "stopOnInteraction": true, "pauseOnMouseEnter": true, "reverseDirection": false, "disableOnInteraction": false } } },
          "tags": ["gallery", "slideshow", "autoplay"]
        },
        {
          "id": "gallery-3d-carousel",
          "componentType": "GalleryPro",
          "name": "3D Carousel",
          "thumbnail": null,
          "i18n": { "en": { "name": "3D Carousel" }, "vi": { "name": "Carousel 3D" } },
          "props": { "layoutMode": "carousel-3d" },
          "tags": ["gallery", "3d", "carousel", "coverflow", "creative"]
        }
      ]
    }
  ]
}
